{
    "Fon Adı": "Garanti Portföy Otuzuncu Serbest (Döviz) Fon",
    "Fon Kodu": "GRO",
    "Fonun Eşik Değeri": "%100 BIST-KYD 1 Aylık Mevduat USD Endeksi",
    "Fonun Karşılaştırma Ölçütü": null,
    "Fonun Halka Arz Tarihi": "08.03.2023",
    "Vergilendirme": "Gerçek kişiler için %17.5, tüzel kişiler için %0 stopaj",
    "Alım Satım Esasları": "Fon, Garanti BBVA şubeleri, internet ve mobil şube, anlaşmalı dağıtıcılar ve TEFAS üzerinden alınıp satılabilir. Emirler günlük olarak iletilir.",
    "Yıllık Fon Yönetim Ücreti": "%0.96",
    "Yatırım Stratejisi": "Fon toplam değerinin en az %80’i döviz ve döviz cinsi varlık ve işlemlere yatırım yaparak USD bazında getiri sağlamayı hedefler.",
    "Yatırımcı Profili": "Birikimlerini USD bazında değerlendirmek isteyen, yalnızca Nitelikli Yatırımcılar"
}